mtmtool/__init__.py
mtmtool/download.py
mtmtool/io.py
mtmtool/log.py
mtmtool/notify.py
mtmtool/path.py
mtmtool/pool.py
mtmtool/time.py
mtmtool/extensions/__init__.py
mtmtool/extensions/matplotlib.py
mtmtool-1.3.10.dist-info/LICENSE
mtmtool-1.3.10.dist-info/METADATA
mtmtool-1.3.10.dist-info/WHEEL
mtmtool-1.3.10.dist-info/top_level.txt
mtmtool-1.3.10.dist-info/RECORD
