Metadata-Version: 2.1
Name: mtmtool
Version: 1.3.10
Summary: imutum's tool packages
License: Apache License
Classifier: Development Status :: 3 - Alpha
Classifier: Programming Language :: Python :: 3.9
Classifier: Intended Audience :: Developers
Classifier: License :: OSI Approved :: Apache Software License
Classifier: Operating System :: MacOS
Classifier: Operating System :: POSIX :: Linux
Classifier: Operating System :: Microsoft :: Windows
Requires-Python: >=3.9
License-File: LICENSE
Requires-Dist: requests
Requires-Dist: pyyaml
Requires-Dist: dill
Requires-Dist: python-dateutil
